fundar_llms/__init__.py
fundar_llms/_types.py
fundar_llms/cuda.py
fundar_llms/api/__init__.py
fundar_llms/api/interface.py
fundar_llms/api/ollama.py
fundar_llms/api/tokenizers.py
fundar_llms/dimred/__init__.py
fundar_llms/dimred/projections.py
fundar_llms/dimred/tsne.py
fundar_llms/dimred/umap.py
fundar_llms/reranking/__init__.py
fundar_llms/reranking/cross_encoder.py
fundar_llms/utils/__init__.py
fundar_llms/utils/_dataclass.py
fundar_llms/utils/common.py
fundar_llms/utils/models.py
fundar_llms/utils/uuid.py
fundar_llms/vectorization/__init__.py
fundar_llms/vectorization/documents.py
fundar_llms-1.0.9.dist-info/METADATA
fundar_llms-1.0.9.dist-info/WHEEL
fundar_llms-1.0.9.dist-info/top_level.txt
fundar_llms-1.0.9.dist-info/RECORD
