Metadata-Version: 2.1
Name: fundar-llms
Version: 1.0.9
Summary: LLM utilities created for Fundar's dev projects.
Author: Fundar
Requires-Python: >=3.10
